{".class":"MypyFile","_fullname":"ezdxf.tools.codepage","future_import_flags":[],"is_partial_stub_package":false,"is_stub":false,"names":{".class":"SymbolTable","__annotations__":{".class":"SymbolTableNode","kind":"Gdef","node":{".class":"Var","flags":["is_ready"],"fullname":"ezdxf.tools.codepage.__annotations__","name":"__annotations__","type":{".class":"Instance","args":["builtins.str",{".class":"AnyType","missing_import_name":null,"source_any":null,"type_of_any":6}],"type_ref":"builtins.dict"}}},"__doc__":{".class":"SymbolTableNode","kind":"Gdef","node":{".class":"Var","flags":["is_ready"],"fullname":"ezdxf.tools.codepage.__doc__","name":"__doc__","type":"builtins.str"}},"__file__":{".class":"SymbolTableNode","kind":"Gdef","node":{".class":"Var","flags":["is_ready"],"fullname":"ezdxf.tools.codepage.__file__","name":"__file__","type":"builtins.str"}},"__name__":{".class":"SymbolTableNode","kind":"Gdef","node":{".class":"Var","flags":["is_ready"],"fullname":"ezdxf.tools.codepage.__name__","name":"__name__","type":"builtins.str"}},"__package__":{".class":"SymbolTableNode","kind":"Gdef","node":{".class":"Var","flags":["is_ready"],"fullname":"ezdxf.tools.codepage.__package__","name":"__package__","type":"builtins.str"}},"codepage_to_encoding":{".class":"SymbolTableNode","kind":"Gdef","node":{".class":"Var","flags":["is_inferred","has_explicit_value"],"fullname":"ezdxf.tools.codepage.codepage_to_encoding","name":"codepage_to_encoding","type":{".class":"Instance","args":["builtins.str","builtins.str"],"type_ref":"builtins.dict"}}},"encoding_to_codepage":{".class":"SymbolTableNode","kind":"Gdef","node":{".class":"Var","flags":["is_inferred","has_explicit_value"],"fullname":"ezdxf.tools.codepage.encoding_to_codepage","name":"encoding_to_codepage","type":{".class":"Instance","args":["builtins.str","builtins.str"],"type_ref":"builtins.dict"}}},"is_supported_encoding":{".class":"SymbolTableNode","kind":"Gdef","node":{".class":"FuncDef","abstract_status":0,"arg_kinds":[1],"arg_names":["encoding"],"dataclass_transform_spec":null,"flags":[],"fullname":"ezdxf.tools.codepage.is_supported_encoding","name":"is_supported_encoding","type":{".class":"CallableType","arg_kinds":[1],"arg_names":["encoding"],"arg_types":["builtins.str"],"bound_args":[],"def_extras":{"first_arg":null},"fallback":"builtins.function","from_concatenate":false,"implicit":false,"is_ellipsis_args":false,"name":"is_supported_encoding","ret_type":"builtins.bool","type_guard":null,"unpack_kwargs":false,"variables":[]}}},"tocodepage":{".class":"SymbolTableNode","kind":"Gdef","node":{".class":"FuncDef","abstract_status":0,"arg_kinds":[0],"arg_names":["encoding"],"dataclass_transform_spec":null,"flags":[],"fullname":"ezdxf.tools.codepage.tocodepage","name":"tocodepage","type":{".class":"CallableType","arg_kinds":[0],"arg_names":["encoding"],"arg_types":["builtins.str"],"bound_args":[],"def_extras":{"first_arg":null},"fallback":"builtins.function","from_concatenate":false,"implicit":false,"is_ellipsis_args":false,"name":"tocodepage","ret_type":"builtins.str","type_guard":null,"unpack_kwargs":false,"variables":[]}}},"toencoding":{".class":"SymbolTableNode","kind":"Gdef","node":{".class":"FuncDef","abstract_status":0,"arg_kinds":[0],"arg_names":["dxfcodepage"],"dataclass_transform_spec":null,"flags":[],"fullname":"ezdxf.tools.codepage.toencoding","name":"toencoding","type":{".class":"CallableType","arg_kinds":[0],"arg_names":["dxfcodepage"],"arg_types":["builtins.str"],"bound_args":[],"def_extras":{"first_arg":null},"fallback":"builtins.function","from_concatenate":false,"implicit":false,"is_ellipsis_args":false,"name":"toencoding","ret_type":"builtins.str","type_guard":null,"unpack_kwargs":false,"variables":[]}}}},"path":"C:\\Users\\Asus\\crowd\\.venv\\Lib\\site-packages\\ezdxf\\tools\\codepage.py"}